typed_dydx/__init__.py
typed_dydx-0.1.0.dist-info/METADATA
typed_dydx-0.1.0.dist-info/WHEEL
typed_dydx-0.1.0.dist-info/top_level.txt
typed_dydx-0.1.0.dist-info/RECORD
